LICENSE
MANIFEST.in
README.md
setup.cfg
setup.py
django_s3_folder_storage.egg-info/PKG-INFO
django_s3_folder_storage.egg-info/SOURCES.txt
django_s3_folder_storage.egg-info/dependency_links.txt
django_s3_folder_storage.egg-info/requires.txt
django_s3_folder_storage.egg-info/top_level.txt
s3_folder_storage/__init__.py
s3_folder_storage/models.py
s3_folder_storage/s3.py
s3_folder_storage/tests/__init__.py
s3_folder_storage/tests/testS3.py
s3_folder_storage/tests/testapp/__init__.py
s3_folder_storage/tests/testapp/models.py