Metadata-Version: 1.1
Name: django-s3-folder-storage
Version: 0.5
Summary: Quick extension of django-storages' S3BotoStorage to allow separate folders for uploaded and static media within an S3 bucket.
Home-page: https://github.com/jamstooks/django-s3-folder-storage
Author: Benjamin W Stookey
Author-email: ben.stookey@gmail.com
License: UNKNOWN
Platform: UNKNOWN
Classifier: Environment :: Web Environment
Classifier: Intended Audience :: Developers
Classifier: License :: OSI Approved :: BSD License
Classifier: Operating System :: OS Independent
Classifier: Programming Language :: Python :: 2.6
Classifier: Programming Language :: Python :: 2.7
Classifier: Framework :: Django
